tilebox/datasets/__init__.py
tilebox/datasets/client.py
tilebox/datasets/group.py
tilebox/datasets/message_pool.py
tilebox/datasets/progress.py
tilebox/datasets/service.py
tilebox/datasets/uuid.py
tilebox/datasets/aio/__init__.py
tilebox/datasets/aio/client.py
tilebox/datasets/aio/dataset.py
tilebox/datasets/aio/pagination.py
tilebox/datasets/aio/timeseries.py
tilebox/datasets/buf/validate/validate_pb2.py
tilebox/datasets/buf/validate/validate_pb2.pyi
tilebox/datasets/buf/validate/validate_pb2_grpc.py
tilebox/datasets/data/__init__.py
tilebox/datasets/data/collection.py
tilebox/datasets/data/data_access.py
tilebox/datasets/data/datapoint.py
tilebox/datasets/data/datasets.py
tilebox/datasets/data/time_interval.py
tilebox/datasets/data/timeseries.py
tilebox/datasets/datasets/v1/collections_pb2.py
tilebox/datasets/datasets/v1/collections_pb2.pyi
tilebox/datasets/datasets/v1/collections_pb2_grpc.py
tilebox/datasets/datasets/v1/core_pb2.py
tilebox/datasets/datasets/v1/core_pb2.pyi
tilebox/datasets/datasets/v1/core_pb2_grpc.py
tilebox/datasets/datasets/v1/data_access_pb2.py
tilebox/datasets/datasets/v1/data_access_pb2.pyi
tilebox/datasets/datasets/v1/data_access_pb2_grpc.py
tilebox/datasets/datasets/v1/data_ingestion_pb2.py
tilebox/datasets/datasets/v1/data_ingestion_pb2.pyi
tilebox/datasets/datasets/v1/data_ingestion_pb2_grpc.py
tilebox/datasets/datasets/v1/dataset_type_pb2.py
tilebox/datasets/datasets/v1/dataset_type_pb2.pyi
tilebox/datasets/datasets/v1/dataset_type_pb2_grpc.py
tilebox/datasets/datasets/v1/datasets_pb2.py
tilebox/datasets/datasets/v1/datasets_pb2.pyi
tilebox/datasets/datasets/v1/datasets_pb2_grpc.py
tilebox/datasets/datasets/v1/timeseries_pb2.py
tilebox/datasets/datasets/v1/timeseries_pb2.pyi
tilebox/datasets/datasets/v1/timeseries_pb2_grpc.py
tilebox/datasets/datasets/v1/well_known_types_pb2.py
tilebox/datasets/datasets/v1/well_known_types_pb2.pyi
tilebox/datasets/datasets/v1/well_known_types_pb2_grpc.py
tilebox_datasets-0.48.0.dist-info/METADATA
tilebox_datasets-0.48.0.dist-info/WHEEL
tilebox_datasets-0.48.0.dist-info/RECORD
