Metadata-Version: 2.4
Name: tilebox-datasets
Version: 0.48.0
Summary: Access Tilebox datasets from Python
Project-URL: Homepage, https://tilebox.com
Project-URL: Documentation, https://docs.tilebox.com/datasets/introduction
Author-email: "Tilebox, Inc." <support@tilebox.com>
License: MIT License
Classifier: Intended Audience :: Developers
Classifier: Intended Audience :: Science/Research
Classifier: License :: OSI Approved :: MIT License
Classifier: Operating System :: OS Independent
Classifier: Programming Language :: Python
Classifier: Programming Language :: Python :: 3
Classifier: Programming Language :: Python :: 3.10
Classifier: Programming Language :: Python :: 3.11
Classifier: Programming Language :: Python :: 3.12
Classifier: Programming Language :: Python :: 3.13
Classifier: Topic :: Scientific/Engineering
Classifier: Topic :: Software Development
Requires-Python: >=3.10
Requires-Dist: cftime>=1.6.4
Requires-Dist: loguru>=0.7
Requires-Dist: numpy>=1.24
Requires-Dist: pandas>=2.1
Requires-Dist: promise>=2.3
Requires-Dist: shapely>=2
Requires-Dist: tilebox-grpc>=0.28.0
Requires-Dist: tqdm>=4.65
Requires-Dist: xarray>=2023.11
